{
	"serverInfo": {
		"name": "Ley Abierta",
		"version": "1.0.0",
		"description": "API de legislacion espanola consolidada. Busca, compara versiones y consulta el historial de mas de 12.000 leyes desde 1835."
	},
	"capabilities": {
		"tools": true,
		"resources": true
	},
	"endpoints": {
		"api": "https://api.leyabierta.es/v1/",
		"health": "https://api.leyabierta.es/health"
	},
	"tools": [
		{
			"name": "search_laws",
			"description": "Buscar leyes por texto, rango, estado, materia o jurisdiccion",
			"endpoint": "GET /v1/laws?q={query}&country={country}&rank={rank}&status={status}&materia={materia}"
		},
		{
			"name": "get_law",
			"description": "Obtener una ley completa con metadatos, articulos y reformas",
			"endpoint": "GET /v1/laws/{id}"
		},
		{
			"name": "get_law_history",
			"description": "Obtener la linea temporal de reformas de una ley",
			"endpoint": "GET /v1/laws/{id}/history"
		},
		{
			"name": "get_law_diff",
			"description": "Comparar dos versiones de una ley entre dos fechas",
			"endpoint": "GET /v1/laws/{id}/diff?from={date}&to={date}"
		},
		{
			"name": "get_law_version",
			"description": "Obtener el texto de una ley en una fecha concreta",
			"endpoint": "GET /v1/laws/{id}/versions/{date}"
		},
		{
			"name": "get_law_analysis",
			"description": "Obtener materias, notas y referencias cruzadas de una ley",
			"endpoint": "GET /v1/laws/{id}/analisis"
		},
		{
			"name": "list_ranks",
			"description": "Listar tipos de rango normativo con conteos",
			"endpoint": "GET /v1/ranks"
		},
		{
			"name": "list_materias",
			"description": "Listar categorias tematicas con conteos",
			"endpoint": "GET /v1/materias"
		},
		{
			"name": "get_changelog",
			"description": "Ultimas reformas legislativas con resumenes",
			"endpoint": "GET /v1/changelog?jurisdiction={jurisdiction}&since={date}&limit={n}"
		}
	]
}
